<root main_tree_to_execute="MainTree">
  <BehaviorTree ID="MainTree">
    <RecoveryNode number_of_retries="6" name="NavigateRecovery">
      <Sequence>
        <RateController hz="2.0">
          <RecoveryNode number_of_retries="1" name="ComputePathToPose">
            <Fallback>
              <ComputePathToPose goal="{goal}" path="{path}" planner_id="GridBased"/>
            </Fallback>
            <ClearEntireCostmap name="ClearGlobalCostmap-Context" service_name="global_costmap/clear_entirely_global_costmap"/>
          </RecoveryNode>
        </RateController>
        <RecoveryNode number_of_retries="1" name="FollowPath">
          <FollowPath path="{path}" controller_id="FollowPath"/>
          <ClearEntireCostmap name="ClearLocalCostmap-Context" service_name="local_costmap/clear_entirely_local_costmap"/>
        </RecoveryNode>
      </Sequence>
      <ReactiveFallback name="RecoveryFallback">
        <GoalUpdated/>
        <RoundRobin name="RecoveryActions">
          <Sequence name="ClearingActions">
            <ClearEntireCostmap name="ClearLocalCostmap-Subtree" service_name="local_costmap/clear_entirely_local_costmap"/>
            <ClearEntireCostmap name="ClearGlobalCostmap-Subtree" service_name="global_costmap/clear_entirely_global_costmap"/>
          </Sequence>
          <BackUp backup_dist="0.30" backup_speed="0.5"/>
          <Wait wait_duration="5"/>
        </RoundRobin>
      </ReactiveFallback>
    </RecoveryNode>
  </BehaviorTree>
</root>
